mlp_kan/__init__.py
mlp_kan/interpolation.py
mlp_kan/kan_layer.py
mlp_kan-0.1.0.dist-info/licenses/LICENSE
mlp_kan-0.1.0.dist-info/METADATA
mlp_kan-0.1.0.dist-info/WHEEL
mlp_kan-0.1.0.dist-info/top_level.txt
mlp_kan-0.1.0.dist-info/RECORD
