Metadata-Version: 2.4
Name: mlp-kan
Version: 0.1.0
Summary: Kolmogorov–Arnold Networks layers with MLP and interpolation activations.
Author: Yanbo Zhang
License: MIT License
Project-URL: Homepage, https://github.com/yanbozhang/MLP-KAN
Project-URL: Repository, https://github.com/yanbozhang/MLP-KAN
Project-URL: Issues, https://github.com/yanbozhang/MLP-KAN/issues
Keywords: kolmogorov-arnold network,neural networks,torch,representation learning
Classifier: Development Status :: 3 - Alpha
Classifier: Intended Audience :: Science/Research
Classifier: License :: OSI Approved :: MIT License
Classifier: Programming Language :: Python
Classifier: Programming Language :: Python :: 3
Classifier: Programming Language :: Python :: 3.9
Classifier: Programming Language :: Python :: 3.10
Classifier: Programming Language :: Python :: 3.11
Classifier: Topic :: Scientific/Engineering :: Artificial Intelligence
Requires-Python: >=3.7
License-File: LICENSE
Requires-Dist: torch>=2.0
Dynamic: license-file
